{"format":1,"version":"4.4.2","settings":"0f1df930ba897ef7a886ee01165196b4","files":{"project___init___py":{"hash":"264bd2645cde44e741641214431afdc1","index":{"nums":[1,26,0,12,0,0,0],"html_filename":"project___init___py.html","relative_filename":"project/__init__.py"}},"project_api_models_py":{"hash":"cb806d4d684c831f273324414145a520","index":{"nums":[1,31,0,17,2,0,0],"html_filename":"project_api_models_py.html","relative_filename":"project/api/models.py"}},"project_api_users_py":{"hash":"9e602e5fef7103e7673e895df8a242c2","index":{"nums":[1,49,0,10,10,0,0],"html_filename":"project_api_users_py.html","relative_filename":"project/api/users.py"}},"project_api_auth_py":{"hash":"d9e860cde9f6cfc01b0ab0b75ea9e1ec","index":{"nums":[1,74,0,15,18,4,4],"html_filename":"project_api_auth_py.html","relative_filename":"project/api/auth.py"}}}}